nicetrace/__init__.py
nicetrace/py.typed
nicetrace/serialization.py
nicetrace/tracing.py
nicetrace/data/blob.py
nicetrace/data/html.py
nicetrace/ext/graphviz.py
nicetrace/ext/langchain.py
nicetrace/ext/pyplot.py
nicetrace/html/__init__.py
nicetrace/html/staticfiles.py
nicetrace/html/statichtml.py
nicetrace/html/static/icon.svg
nicetrace/html/static/index-BupuF-VS.css
nicetrace/html/static/index-DoqnF80a.js
nicetrace/html/static/index.html
nicetrace/reader/base.py
nicetrace/reader/filereader.py
nicetrace/server/__init__.py
nicetrace/server/__main__.py
nicetrace/server/app.py
nicetrace/utils/ids.py
nicetrace/writer/base.py
nicetrace/writer/filewriter.py
nicetrace-0.4.10.dist-info/METADATA
nicetrace-0.4.10.dist-info/WHEEL
nicetrace-0.4.10.dist-info/licenses/LICENSE
nicetrace-0.4.10.dist-info/RECORD
