Metadata-Version: 2.3
Name: nicetrace
Version: 0.4.10
Author-email: Ada Bohm <ada@kreatrix.org>
Requires-Python: >=3.10
Provides-Extra: server
Requires-Dist: flask-cors>=5.0.0; extra == 'server'
Requires-Dist: flask>=3.0.3; extra == 'server'
Requires-Dist: waitress>=3.0.0; extra == 'server'
